happy_kostadin/__init__.py
happy_kostadin/__main__.py
happy_kostadin/cli.py
happy_kostadin/get_config/__init__.py
happy_kostadin/get_config/get_args.py
happy_kostadin/get_config/get_config.py
happy_kostadin/get_config/get_toml_values.py
happy_kostadin-0.1.1.dist-info/METADATA
happy_kostadin-0.1.1.dist-info/WHEEL
happy_kostadin-0.1.1.dist-info/entry_points.txt
happy_kostadin-0.1.1.dist-info/licenses/LICENSE
happy_kostadin-0.1.1.dist-info/RECORD
