Metadata-Version: 2.4
Name: happy_kostadin
Version: 0.1.1
Author-email: Tom Nijhof <tomsspamadress@gmail.com>
License: Apache-2.0
License-File: LICENSE
Keywords: checker,crlf,lf,line-ending
Classifier: Development Status :: 4 - Beta
Classifier: Environment :: Console
Classifier: Intended Audience :: Developers
Classifier: Intended Audience :: System Administrators
Classifier: License :: OSI Approved :: Apache Software License
Classifier: Operating System :: OS Independent
Classifier: Programming Language :: Python
Classifier: Programming Language :: Python :: 3
Classifier: Programming Language :: Python :: 3 :: Only
Classifier: Programming Language :: Python :: 3.9
Classifier: Programming Language :: Python :: 3.10
Classifier: Programming Language :: Python :: 3.11
Classifier: Programming Language :: Python :: 3.12
Classifier: Programming Language :: Python :: 3.13
Requires-Python: >=3.9
Requires-Dist: setuptools>=62
Requires-Dist: tomli>=1.1.0; python_version < '3.11'
Requires-Dist: tqdm>=4.66.1
